LICENSE
MANIFEST.in
readme.md
requirements.txt
setup.py
MockupEngineer/__init__.py
MockupEngineer/__main__.py
MockupEngineer.egg-info/PKG-INFO
MockupEngineer.egg-info/SOURCES.txt
MockupEngineer.egg-info/dependency_links.txt
MockupEngineer.egg-info/requires.txt
MockupEngineer.egg-info/top_level.txt
MockupEngineer/templates/__init__.py
MockupEngineer/templates/console_example.png
MockupEngineer/templates/galaxys20/blue.png
MockupEngineer/templates/galaxys20/config.ini
MockupEngineer/templates/galaxys20/grey.png
MockupEngineer/templates/galaxys20/mask.png
MockupEngineer/templates/galaxys20/pink.png
MockupEngineer/templates/galaxys20/preview.png
MockupEngineer/templates/galaxys20ultra/black.png
MockupEngineer/templates/galaxys20ultra/config.ini
MockupEngineer/templates/galaxys20ultra/grey.png
MockupEngineer/templates/galaxys20ultra/mask.png
MockupEngineer/templates/galaxys20ultra/preview.png
MockupEngineer/templates/imac212015/config.ini
MockupEngineer/templates/imac212015/preview.png
MockupEngineer/templates/imac212015/silver.png
MockupEngineer/templates/imac242021/blue.png
MockupEngineer/templates/imac242021/config.ini
MockupEngineer/templates/imac242021/green.png
MockupEngineer/templates/imac242021/orange.png
MockupEngineer/templates/imac242021/pink.png
MockupEngineer/templates/imac242021/preview.png
MockupEngineer/templates/imac242021/purple.png
MockupEngineer/templates/imac242021/silver.png
MockupEngineer/templates/imac242021/yellow.png
MockupEngineer/templates/ipad9/config.ini
MockupEngineer/templates/ipad9/gold.png
MockupEngineer/templates/ipad9/preview.png
MockupEngineer/templates/ipad9/silver.png
MockupEngineer/templates/ipad9/spacegray.png
MockupEngineer/templates/ipadair4/config.ini
MockupEngineer/templates/ipadair4/green.png
MockupEngineer/templates/ipadair4/preview.png
MockupEngineer/templates/ipadair4/rosegold.png
MockupEngineer/templates/ipadair4/silver.png
MockupEngineer/templates/ipadair4/skyblue.png
MockupEngineer/templates/ipadair4/spacegray.png
MockupEngineer/templates/ipadmini5/config.ini
MockupEngineer/templates/ipadmini5/gold.png
MockupEngineer/templates/ipadmini5/preview.png
MockupEngineer/templates/ipadmini5/silver.png
