Metadata-Version: 2.1
Name: MockupEngineer
Version: 2022.2.24.1
Summary: A simple library for creating beautiful screenshots.
Home-page: https://github.com/ulbwazhine/MockupEngineer
Author: Ulbwazhine
Author-email: ulbwa@icloud.com
License: MIT
Platform: UNKNOWN
License-File: LICENSE
